timeback_common/__init__.py
timeback_common/config.py
timeback_common/create_response.py
timeback_common/datetime.py
timeback_common/errors.py
timeback_common/filter.py
timeback_common/normalization.py
timeback_common/pagination.py
timeback_common/pagination_strategies.py
timeback_common/provider.py
timeback_common/py.typed
timeback_common/resolve.py
timeback_common/token_manager.py
timeback_common/transport.py
timeback_common/validation.py
timeback_common-0.1.4.dist-info/METADATA
timeback_common-0.1.4.dist-info/WHEEL
timeback_common-0.1.4.dist-info/RECORD
