Metadata-Version: 2.4
Name: timeback-common
Version: 0.1.4
Summary: Shared infrastructure for Timeback Python clients
Project-URL: Homepage, https://developer.timeback.com
Project-URL: Documentation, https://docs.timeback.com
Project-URL: Repository, https://github.com/superbuilders/timeback-dev-python
Author-email: Timeback <dev@timeback.dev>
License-Expression: MIT
Classifier: Development Status :: 3 - Alpha
Classifier: Intended Audience :: Developers
Classifier: License :: OSI Approved :: MIT License
Classifier: Programming Language :: Python :: 3
Classifier: Programming Language :: Python :: 3.12
Classifier: Programming Language :: Python :: 3.13
Classifier: Typing :: Typed
Requires-Python: >=3.12
Requires-Dist: httpx>=0.27
Requires-Dist: pydantic>=2.0
